{
  "champ": {"repro2016": {"policy": "keep_after_and_before" , "start_date": "2001-139" , "end_date": "2008-279"}},
  "cnofs": {"postProc": {"policy": "keep_after_and_before" , "start_date": "2010-060" , "end_date": "2011-365"}},
  "cosmic1": {"postProc": {"policy": "keep_after_and_before" , "start_date":  "2014-121" , "end_date": "2020-116"},
              "repro2013": {"policy": "keep_after_and_before" , "start_date": "2006-112" , "end_date": "2014-120"},
              "repro2021": {"policy": "keep_none" , "start_date": "2006-120" , "end_date": "2019-344"}},
  "cosmic2": {"nrt": {"policy": "keep_after" , "start_date": "2019-274" , "end_date": ""},
              "postProc": {"policy": "keep_none" , "start_date": "2019-213" , "end_date": "2021-031"},
              "provisional/release1": {"policy": "keep_none" , "start_date": "2019-274" , "end_date": "2020-047"},
              "provisional/spaceWeather": {"policy": "keep_none" , "start_date": "2019-274" , "end_date": ""},
              "rapid": {"policy": "keep_none" , "start_date": "2022-084" , "end_date": ""},
              "tools": {"policy": "keep_none" , "start_date": "" , "end_date": ""}},
  "fid": {"nrt": {"policy": "keep_none" , "start_date": "2019-001" , "end_date": "2021-301"}},
  "geoopt": {"noaa/nrt": {"policy": "keep_none" , "start_date": "2020-350" , "end_date": "2022-294"},
             "noaa/postProc": {"policy": "keep_after_and_before" , "start_date": "2020-336" , "end_date": "2021-259"}},
  "gpsmet": {"postProc": {"policy": "keep_after_and_before" , "start_date": "1995-111" , "end_date": "1997-047"}},
  "gpsmetas": {"postProc": {"policy": "keep_after_and_before" , "start_date": "1995-237" , "end_date": "1997-016"}},
  "grace": {"postProc": {"policy": "keep_after_and_before" , "start_date": "2007-059" , "end_date": "2017-334"}},
  "kompsat5": {"postProc": {"policy": "keep_after" , "start_date": "2015-022" , "end_date": ""},
             "nrt":{"policy": "keep_none" , "start_date": "2022-200" , "end_date": ""}},
  "metopa": {"postProc": {"policy": "keep_after" , "start_date": "2016-001" , "end_date": ""},
             "repro2016": {"policy": "keep_after_and_before" , "start_date": "2007-274" , "end_date": "2015-365"}},
  "metopb": {"postProc": {"policy": "keep_after" , "start_date": "2016-001" , "end_date": ""},
             "repro2016": {"policy": "keep_after_and_before" , "start_date": "2013-032" , "end_date": "2015-365"}},
  "metopc": {"postProc": {"policy": "keep_after" , "start_date": "2019-195" , "end_date": ""}},
  "paz": {"postProc": {"policy": "keep_after" , "start_date": "2018-130" , "end_date": ""},
             "nrt":{"policy": "keep_none" , "start_date": "2023-001" , "end_date": ""}},
  "planetiq": {"noaa/nrt": {"policy": "keep_none" , "start_date": "2023-095" , "end_date": ""},
	     "noaa/postProc": {"policy": "keep_after" , "start_date": "2023-095" , "end_date": ""}},
  "publications": {"hthh2022": {"policy": "keep_none" , "start_date": "2022-001" , "end_date": ""}},
  "sacc": {"postProc": {"policy": "keep_after_and_before" , "start_date": "2006-068" , "end_date": "2011-215"}},
  "spire": {"noaa/nrt": {"policy": "keep_after" , "start_date": "2020-350" , "end_date": ""}},
  "tdx": {"postProc": {"policy": "keep_after" , "start_date": "2020-366" , "end_date": ""}},
  "tsx": {"postProc": {"policy": "keep_after" , "start_date": "2020-366" , "end_date": ""}}
}
